{
  "project_info": {
    "project_number": "186915196450",
    "firebase_url": "https://goli-5cefe.firebaseio.com",
    "project_id": "goli-5cefe",
    "storage_bucket": "goli-5cefe.appspot.com"
  },
  "client": [
    {
      "client_info": {
        "mobilesdk_app_id": "1:186915196450:android:610bab1c08531070f3847b",
        "android_client_info": {
          "package_name": "com.balik.goli"
        }
      },
      "oauth_client": [
        {
          "client_id": "186915196450-dh9dumaia4575uoantaicd3o37gp86l9.apps.googleusercontent.com",
          "client_type": 3
        }
      ],
      "api_key": [
        {
          "current_key": "AIzaSyBZl6TzLvylRiL-yJ2MXAY_I7wdW0QRmVQ"
        }
      ],
      "services": {
        "appinvite_service": {
          "other_platform_oauth_client": [
            {
              "client_id": "186915196450-dh9dumaia4575uoantaicd3o37gp86l9.apps.googleusercontent.com",
              "client_type": 3
            }
          ]
        }
      }
    }
  ],
  "configuration_version": "1"
}